sbio/__init__.py
sbio/fastq_quality.py
sbio-0.0.7.dist-info/LICENSE
sbio-0.0.7.dist-info/METADATA
sbio-0.0.7.dist-info/WHEEL
sbio-0.0.7.dist-info/top_level.txt
sbio-0.0.7.dist-info/RECORD
